prefect_rw/__init__.py
prefect_rw/py.typed
prefect_rw/rw_process_worker.py
prefect_rw/rw_pull.py
prefect_rw/rw_storage.py
prefect_rw/to_tray.py
prefect_rw/wrapper.py
prefect_rw-0.1.7.dist-info/WHEEL
prefect_rw-0.1.7.dist-info/METADATA
prefect_rw-0.1.7.dist-info/RECORD
