Metadata-Version: 2.4
Name: prefect-rw
Version: 0.1.7
Summary: Add your description here
Author: Maksim Sukhanov
Author-email: Maksim Sukhanov <kakxow@gmail.com>
License-Expression: WTFPL
Requires-Dist: prefect>=3.4.14
Requires-Dist: psutil>=7.1.3
Requires-Dist: pystray>=0.19.5
Requires-Python: >=3.11
